batch/__init__.py
batch/batch.py
batch/torch_patch.py
batch/utils.py
batch_dev-0.0.3.dist-info/LICENSE
batch_dev-0.0.3.dist-info/METADATA
batch_dev-0.0.3.dist-info/WHEEL
batch_dev-0.0.3.dist-info/top_level.txt
batch_dev-0.0.3.dist-info/RECORD
