Metadata-Version: 2.1
Name: batch-dev
Version: 0.0.3
Summary: Generic python module for handling dictionary-based batch data
Home-page: https://github.com/Peter-Kocsis/batch
Author: Peter Kocsis
Author-email: peti0510@gmail.com
Project-URL: Bug Reports, https://github.com/Peter-Kocsis/batch/issues
Project-URL: Source, https://github.com/Peter-Kocsis/batch
Keywords: data-processing,datastructure,machine-learning,deep-learning,ml,pytorch,numpy
Classifier: Development Status :: 4 - Beta
Classifier: Intended Audience :: Developers
Classifier: Operating System :: OS Independent
Classifier: Topic :: Education
Classifier: Topic :: Scientific/Engineering
Classifier: Topic :: Scientific/Engineering :: Artificial Intelligence
Classifier: License :: OSI Approved :: MIT License
Classifier: Programming Language :: Python :: 3.8
Classifier: Programming Language :: Python :: 3.9
Classifier: Programming Language :: Python :: 3.10
Classifier: Programming Language :: Python :: 3.11
Classifier: Programming Language :: Python :: 3.12
Requires-Python: >=3.8, <4
License-File: LICENSE
